nagra_network_paloalto_utils/__init__.py
nagra_network_paloalto_utils/__main__.py
nagra_network_paloalto_utils/commands/__init__.py
nagra_network_paloalto_utils/commands/git_writer.py
nagra_network_paloalto_utils/commands/panorama/__init__.py
nagra_network_paloalto_utils/commands/panorama/objects/__init__.py
nagra_network_paloalto_utils/commands/panorama/objects/addresses.py
nagra_network_paloalto_utils/commands/panorama/objects/applications.py
nagra_network_paloalto_utils/commands/panorama/objects/services.py
nagra_network_paloalto_utils/commands/panorama/objects/tags.py
nagra_network_paloalto_utils/commands/panorama/panorama.py
nagra_network_paloalto_utils/commands/terraform/__init__.py
nagra_network_paloalto_utils/commands/terraform/object_deletion_checker.py
nagra_network_paloalto_utils/commands/yaml/__init__.py
nagra_network_paloalto_utils/commands/yaml/checks.py
nagra_network_paloalto_utils/commands/yaml/indexes.py
nagra_network_paloalto_utils/utils/__init__.py
nagra_network_paloalto_utils/utils/addresses.py
nagra_network_paloalto_utils/utils/addresses_remove.py
nagra_network_paloalto_utils/utils/applications.py
nagra_network_paloalto_utils/utils/checks.py
nagra_network_paloalto_utils/utils/common/__init__.py
nagra_network_paloalto_utils/utils/common/remove.py
nagra_network_paloalto_utils/utils/common/utils.py
nagra_network_paloalto_utils/utils/common/yamlizer.py
nagra_network_paloalto_utils/utils/constants.py
nagra_network_paloalto_utils/utils/git_writer.py
nagra_network_paloalto_utils/utils/indexes.py
nagra_network_paloalto_utils/utils/locking_panorama.py
nagra_network_paloalto_utils/utils/object_deletion_checker.py
nagra_network_paloalto_utils/utils/panorama.py
nagra_network_paloalto_utils/utils/rules_getter.py
nagra_network_paloalto_utils/utils/services.py
nagra_network_paloalto_utils/utils/tags.py
nagra_network_paloalto_utils-0.1.31.dist-info/METADATA
nagra_network_paloalto_utils-0.1.31.dist-info/WHEEL
nagra_network_paloalto_utils-0.1.31.dist-info/entry_points.txt
nagra_network_paloalto_utils-0.1.31.dist-info/RECORD
