Metadata-Version: 2.3
Name: nagra_network_paloalto_utils
Version: 0.1.31
Summary: 
Author: David Gallay
Author-email: david.gallay@nagra.com
Requires-Python: >=3.9,<4.0
Classifier: Programming Language :: Python :: 3
Classifier: Programming Language :: Python :: 3.9
Classifier: Programming Language :: Python :: 3.10
Classifier: Programming Language :: Python :: 3.11
Classifier: Programming Language :: Python :: 3.12
Classifier: Programming Language :: Python :: 3.13
Requires-Dist: click (>=8.1.7,<9.0.0)
Requires-Dist: colorama (>=0.4.4)
Requires-Dist: gitpython (>=0.3.6)
Requires-Dist: glom (>=23.4.0,<24.0.0)
Requires-Dist: nagra-network-misc-utils (==0.2.7)
Requires-Dist: nagra-panorama-api (==0.2.7)
Requires-Dist: pyyaml (>=0.2.5)
Requires-Dist: requests (>=2.31.0,<3.0.0)
Requires-Dist: ruamel-yaml (>=0.17.21)
Requires-Dist: urllib3 (>=1.26.4)
Requires-Dist: xmltodict (>=0.13.0)
